Workbook

Sheet Summary
A1: Summary
A3: Key Output | H3: Note
C4: Debt sizing
D5: =Model!D141 -> Target debt size | E5: =Model!E141 -> 1.3182507e+08 | F5: AUD | H5: The DSCR sized debt represents ~60% of total project cost (57.7% of total project cost & IDC), which are both lower than the 60% expectation
C7: Key metrics and returns
D8: =Model!D181 -> Min. DSCR | E8: =Model!E181 -> 1.3499743
D9: =Model!D182 -> Average DSCR | E9: =Model!E182 -> 1.3631561
D10: =Model!D190 -> LLCR | E10: =Model!E190 -> 1.2296298
D11: P-IRR | E11: =Model!E236 -> 0.03859863 | H11: P-IRR (3.9%) is low due to the interest tax shield. The levered entity generates a NOL pool from Years 1–5 interest deductions, deferring tax payments through Year 20. On an unlevered basis, tax is payable from Year 1 with no carry-forward, reducing early-year cash flows. The spread represents the timing value of the tax shield, not project underperformance.
D12: =Model!D245 -> Debt IRR | E12: =Model!E245 -> 0.06492596
D13: =Model!D251 -> Equity IRR | E13: =Model!E251 -> 0.041328928 | H13: E-IRR suppressed at 4.1% due to no refi modelled at mini-perm maturity. Dividends commence Year 14. True E-IRR contingent on refinancing terms.
F14: PPA Price | G14: Merchant Price (2028)
D15: Breakeven price factor | E15: 0.80982037 | F15: =75*$E15 -> 60.736528 | G15: =55*E15 -> 44.54012 | H15: adjusted in Input!E32
C17: Merchant exposure
D18: =Model!D299 -> Merchant Intensity | E18: =Model!E299 -> 0.54149555

Sheet Sensitivity
A1: Sensitivity
D2: Sensitivities | L2: Methodology
D3: Scenario | E3: Debt size (AUD) | F3: Min.DSCR | G3: Avg DSCR | H3: LLCR | I3: P-IRR | J3: D-IRR | K3: E-IRR
D4: Base (Live) | E4: =Summary!E5 -> 1.3182507e+08 | F4: =Summary!E8 -> 1.3499743 | G4: =Summary!E9 -> 1.3631561 | H4: =Summary!E10 -> 1.2296298 | I4: =Summary!E11 -> 0.03859863 | J4: =Summary!E12 -> 0.06492596 | K4: =Summary!E13 -> 0.041328928
D5: Spot -15% | E5: 1.2405967e+08 | F5: 1.3497696 | G5: 1.3667281 | H5: 1.1681431 | I5: 0.027703962 | J5: 0.064925942 | K5: 0.026049086 | L5: Spot price (2028) * 0.85
D6: P90 generation | E6: 1.1391635e+08 | F6: 1.3492499 | G6: 1.3660112 | H6: 1.240056 | I6: 0.028936651 | J6: 0.064925948 | K6: 0.027582631 | L6: Net capacity factor * 0.9
D7: Curtailment +5% | E7: 1.2908542e+08 | F7: 1.3500616 | G7: 1.3645194 | H7: 1.209595 | I7: 0.035012767 | J7: 0.064925954 | K7: 0.036205831 | L7: Negative pricing co-efficient +5%
D8: OPEX +10% | E8: 1.2702305e+08 | F8: 1.3501302 | G8: 1.3665349 | H8: 1.2269927 | I8: 0.035432938 | J8: 0.064925948 | K8: 0.03667089 | L8: Fixed OPEX * 1.1
D9: MLF 0.82 | E9: 1.1959055e+08 | F9: 1.3497751 | G9: 1.365286 | H9: 1.2370956 | I9: 0.03211976 | J9: 0.064925948 | K9: 0.031888893 | L9: MLF = 0.82
D10: Interest + 1% | E10: 1.2046748e+08 | F10: 1.3499739 | G10: 1.3631556 | H10: 1.2400459 | I10: 0.03846958 | J10: 0.074914005 | K10: 0.038653979 | L10: Interest rate + 1%

Sheet Input
A1: Input
A2: Assumption | E2: Input | F2: Input | G2: Unit | H2: Note
A3: Dates
D4: Financial Close | E4: =DATE(2026,12,31) -> 46387 | G4: date
D5: Construction | E5: 12 | G5: months | H5: straight line capex spend in 2027
D6: Commercial Operation | E6: =EOMONTH(E4 - 1, E5) + 1 -> 46753 | G6: date
D7: Operation | E7: 35 | G7: years
D8: Decommissioning | E8: =EOMONTH(E6 - 1, E7 * 12) -> 59536 | G8: date
A10: Generation
D11: Installed capacity | E11: 200 | G11: MWdc | H11: as per page 1
D12: Installed capacity | E12: 160 | G12: MWac | H12: as per page 1
D13: Net capacity factor (P50) | E13: 0.24
D14: Degradation | E14: 0.005 | G14: p.a. | H14: compounding from year 2
D15: Marginal Loss Factor (MLF) | E15: 0.88 | H15: static for the project life
A17: Capital Cost
D18: Total EPC & connection cost | E18: 220000000 | G18: AUD
D19: Total project cost | E19: =SUM(E18:E18) -> 220000000 | G19: AUD
D21: Useful life | E21: 20 | G21: years
A23: Construction loan
E24: Debt | F24: Equity
D25: Funding source | E25: 65 | F25: 35 | G25: %
D26: Gearing ratio (D/C) | E26: =E25/SUM(E25:F25) -> 0.65
D27: Construction loan facility | E27: =E19*E26 -> 143000000 | G27: AUD
D28: Equity contribution | E28: =E19-E27 -> 77000000 | G28: AUD
A30: Revenue
D31: =Summary!D15 -> Breakeven price factor | E31: 1 | H31: affects PPA price and Spot price (2028)
B33: Contracted revenue
D34: Volume | E34: 0.65
D35: PPA price | E35: =E31*75 -> 75 | G35: AUD/MWh | H35: no escalation
D36: PPA tenor | E36: 10 | G36: years
B38: Spot revenue
D39: Volume | E39: =1-E34 -> 0.35
D40: Spot price (2028) | E40: =E31*55 -> 55 | G40: AUD/MWh
D41: Spot price escalation | E41: 0.02 | G41: p.a.
D42: Negative pricing co-efficient | E42: 0.05 | H42: 5% of merchant volume is lost / curtailed due to negative prices (ie. no revenue)
A44: Operational Expense
D45: Fixed OPEX & AEMO fees (per MWac) | E45: 30000 | G45: AUD/MWac/yr
D46: Fixed OPEX & AEMO fees | E46: =E45*E12 -> 4800000 | G46: AUD/yr
D47: Operating expense escalation | E47: 0.025 | G47: p.a. | H47: compounding from year 2
C49: Working Capital
D50: AR days | E50: 0 | G50: days
D51: AP days | E51: 0 | G51: days
A53: Tax
D54: Corporate tax rate | E54: 0.3 | H54: straight line depreciation over 20 years
A56: Financing
C57: Mini-perm
D58: Tenor | E58: 5 | G58: years
D59: Target DSCR | E59: 1.35
D60: Notional repayment profile | E60: 25 | G60: years
D61: Interest rate | E61: 0.065 | G61: p.a. | H61: All-in swapped rate of 6.50% p.a. (BBSY + Margin)
C63: DSRA
D64: DSRA months required | E64: 6 | G64: months
D65: Letter of credit fee | E65: 0.02 | G65: p.a.

Sheet Model
A1: Model
D2: Months per period | E2: 12
D3: Period number | K3: 1 | L3: =K3+1 -> 2 | M3: =L3+1 -> 3 | N3: =M3+1 -> 4 | O3: =N3+1 -> 5 | P3: =O3+1 -> 6 | Q3: =P3+1 -> 7 | R3: =Q3+1 -> 8 | S3: =R3+1 -> 9 | ... AU3: =AT3+1 -> 37
D4: BoP | K4: =J5+1 -> 46388 | L4: =K5+1 -> 46753 | M4: =L5+1 -> 47119 | N4: =M5+1 -> 47484 | O4: =N5+1 -> 47849 | P4: =O5+1 -> 48214 | Q4: =P5+1 -> 48580 | R4: =Q5+1 -> 48945 | ... AU4: =AT5+1 -> 59537
D5: EoP | J5: =Input!E4 -> 46387 | K5: =EOMONTH(K4-1, $E$2) -> 46752 | L5: =EOMONTH(L4-1, $E$2) -> 47118 | M5: =EOMONTH(M4-1, $E$2) -> 47483 | N5: =EOMONTH(N4-1, $E$2) -> 47848 | O5: =EOMONTH(O4-1, $E$2) -> 48213 | P5: =EOMONTH(P4-1, $E$2) -> 48579 | Q5: =EOMONTH(Q4-1, $E$2) -> 48944 | R5: =EOMONTH(R4-1, $E$2) -> 49309 | ... AU5: =EOMONTH(AU4-1, $E$2) -> 59901
D6: Year | K6: =YEAR(K4) -> 2027 | L6: =YEAR(L4) -> 2028 | M6: =YEAR(M4) -> 2029 | N6: =YEAR(N4) -> 2030 | O6: =YEAR(O4) -> 2031 | P6: =YEAR(P4) -> 2032 | Q6: =YEAR(Q4) -> 2033 | R6: =YEAR(R4) -> 2034 | ... AU6: =YEAR(AU4) -> 2063
E7: Assumption | F7: Assumption | G7: Date | H7: Date | I7: Unit | J7: Sum
A8: Timing
D9: COD flag | G9: =Input!E6 -> 46753 | K9: =($G9=K$4)*1 -> 0 | L9: =($G9=L$4)*1 -> 1 | M9: =($G9=M$4)*1 -> 0 | N9: =($G9=N$4)*1 -> 0 | O9: =($G9=O$4)*1 -> 0 | P9: =($G9=P$4)*1 -> 0 | Q9: =($G9=Q$4)*1 -> 0 | R9: =($G9=R$4)*1 -> 0 | ... AU9: =($G9=AU$4)*1 -> 0
D10: Years of operation | E10: =Input!E7 -> 35 | I10: years
D11: PPA Life | E11: =Input!E36 -> 10 | I11: years
D13: Construction period flag | G13: =Input!E4+1 -> 46388 | H13: =G9-1 -> 46752 | K13: =AND(K$4>=$G13, K$5<=$H13) * 1 -> 1 | L13: =AND(L$4>=$G13, L$5<=$H13) * 1 -> 0 | M13: =AND(M$4>=$G13, M$5<=$H13) * 1 -> 0 | N13: =AND(N$4>=$G13, N$5<=$H13) * 1 -> 0 | O13: =AND(O$4>=$G13, O$5<=$H13) * 1 -> 0 | P13: =AND(P$4>=$G13, P$5<=$H13) * 1 -> 0 | Q13: =AND(Q$4>=$G13, Q$5<=$H13) * 1 -> 0 | R13: =AND(R$4>=$G13, R$5<=$H13) * 1 -> 0 | ... AU13: =AND(AU$4>=$G13, AU$5<=$H13) * 1 -> 0
D14: Operating period flag | G14: =G9 -> 46753 | H14: =EOMONTH(G14 - 1, E10 * 12) -> 59536 | K14: =AND(K$4>=$G14, K$5<=$H14) * 1 -> 0 | L14: =AND(L$4>=$G14, L$5<=$H14) * 1 -> 1 | M14: =AND(M$4>=$G14, M$5<=$H14) * 1 -> 1 | N14: =AND(N$4>=$G14, N$5<=$H14) * 1 -> 1 | O14: =AND(O$4>=$G14, O$5<=$H14) * 1 -> 1 | P14: =AND(P$4>=$G14, P$5<=$H14) * 1 -> 1 | Q14: =AND(Q$4>=$G14, Q$5<=$H14) * 1 -> 1 | R14: =AND(R$4>=$G14, R$5<=$H14) * 1 -> 1 | ... AU14: =AND(AU$4>=$G14, AU$5<=$H14) * 1 -> 0
D15: PPA period flag | G15: =G9 -> 46753 | H15: =EOMONTH(G15 - 1, E11 * 12) -> 50405 | K15: =AND(K$4>=$G15, K$5<=$H15) * 1 -> 0 | L15: =AND(L$4>=$G15, L$5<=$H15) * 1 -> 1 | M15: =AND(M$4>=$G15, M$5<=$H15) * 1 -> 1 | N15: =AND(N$4>=$G15, N$5<=$H15) * 1 -> 1 | O15: =AND(O$4>=$G15, O$5<=$H15) * 1 -> 1 | P15: =AND(P$4>=$G15, P$5<=$H15) * 1 -> 1 | Q15: =AND(Q$4>=$G15, Q$5<=$H15) * 1 -> 1 | R15: =AND(R$4>=$G15, R$5<=$H15) * 1 -> 1 | ... AU15: =AND(AU$4>=$G15, AU$5<=$H15) * 1 -> 0
D17: Operating period counter | K17: =J17+K14 -> 0 | L17: =K17+L14 -> 1 | M17: =L17+M14 -> 2 | N17: =M17+N14 -> 3 | O17: =N17+O14 -> 4 | P17: =O17+P14 -> 5 | Q17: =P17+Q14 -> 6 | R17: =Q17+R14 -> 7 | ... AU17: =AT17+AU14 -> 35
A19: Operation
D20: =D$9 -> COD flag | K20: =K$9 -> 0 | L20: =L$9 -> 1 | M20: =M$9 -> 0 | N20: =N$9 -> 0 | O20: =O$9 -> 0 | P20: =P$9 -> 0 | Q20: =Q$9 -> 0 | R20: =R$9 -> 0 | ... AU20: =AU$9 -> 0
D21: =D$14 -> Operating period flag | K21: =K$14 -> 0 | L21: =L$14 -> 1 | M21: =M$14 -> 1 | N21: =N$14 -> 1 | O21: =O$14 -> 1 | P21: =P$14 -> 1 | Q21: =Q$14 -> 1 | R21: =R$14 -> 1 | ... AU21: =AU$14 -> 0
D22: =D$15 -> PPA period flag | K22: =K$15 -> 0 | L22: =L$15 -> 1 | M22: =M$15 -> 1 | N22: =N$15 -> 1 | O22: =O$15 -> 1 | P22: =P$15 -> 1 | Q22: =Q$15 -> 1 | R22: =R$15 -> 1 | ... AU22: =AU$15 -> 0
B24: Revenue
C25: Volume
D26: =Input!D12 -> Installed capacity | E26: =Input!E12 -> 160 | I26: MWac | K26: =$E26 -> 160 | L26: =$E26 -> 160 | M26: =$E26 -> 160 | N26: =$E26 -> 160 | O26: =$E26 -> 160 | P26: =$E26 -> 160 | Q26: =$E26 -> 160 | R26: =$E26 -> 160 | ... AU26: =$E26 -> 160
D27: Net Capacity Factor | E27: =Input!E13 -> 0.24 | K27: =$E27 -> 0.24 | L27: =$E27 -> 0.24 | M27: =$E27 -> 0.24 | N27: =$E27 -> 0.24 | O27: =$E27 -> 0.24 | P27: =$E27 -> 0.24 | Q27: =$E27 -> 0.24 | R27: =$E27 -> 0.24 | ... AU27: =$E27 -> 0.24
D28: Hours per period | E28: =365*24 -> 8760 | I28: hrs | K28: =$E28 -> 8760 | L28: =$E28 -> 8760 | M28: =$E28 -> 8760 | N28: =$E28 -> 8760 | O28: =$E28 -> 8760 | P28: =$E28 -> 8760 | Q28: =$E28 -> 8760 | R28: =$E28 -> 8760 | ... AU28: =$E28 -> 8760
D29: Gross generation | I29: MWh | K29: =K26*K27*K28 * K21 -> 0 | L29: =L26*L27*L28 * L21 -> 336384 | M29: =M26*M27*M28 * M21 -> 336384 | N29: =N26*N27*N28 * N21 -> 336384 | O29: =O26*O27*O28 * O21 -> 336384 | P29: =P26*P27*P28 * P21 -> 336384 | Q29: =Q26*Q27*Q28 * Q21 -> 336384 | R29: =R26*R27*R28 * R21 -> 336384 | ... AU29: =AU26*AU27*AU28 * AU21 -> 0
D31: =Input!D14 -> Degradation | E31: =Input!E14 -> 0.005 | K31: =$E31*K21 -> 0 | L31: =$E31*L21 -> 0.005 | M31: =$E31*M21 -> 0.005 | N31: =$E31*N21 -> 0.005 | O31: =$E31*O21 -> 0.005 | P31: =$E31*P21 -> 0.005 | Q31: =$E31*Q21 -> 0.005 | R31: =$E31*R21 -> 0.005 | ... AU31: =$E31*AU21 -> 0
D32: Degradation factor | K32: =IF(K$20=1, 1, J32*(1-K31)) -> 0 | L32: =IF(L$20=1, 1, K32*(1-L31)) -> 1 | M32: =IF(M$20=1, 1, L32*(1-M31)) -> 0.995 | N32: =IF(N$20=1, 1, M32*(1-N31)) -> 0.990025 | O32: =IF(O$20=1, 1, N32*(1-O31)) -> 0.98507488 | P32: =IF(P$20=1, 1, O32*(1-P31)) -> 0.9801495 | Q32: =IF(Q$20=1, 1, P32*(1-Q31)) -> 0.97524875 | R32: =IF(R$20=1, 1, Q32*(1-R31)) -> 0.97037251 | ... AU32: =IF(AU$20=1, 1, AT32*(1-AU31)) -> 0.84330514
D33: =Input!D15 -> Marginal Loss Factor (MLF) | E33: =Input!E15 -> 0.88 | K33: =$E33 -> 0.88 | L33: =$E33 -> 0.88 | M33: =$E33 -> 0.88 | N33: =$E33 -> 0.88 | O33: =$E33 -> 0.88 | P33: =$E33 -> 0.88 | Q33: =$E33 -> 0.88 | R33: =$E33 -> 0.88 | ... AU33: =$E33 -> 0.88
D34: Net generation | I34: MWh | K34: =K29*K32*K33 -> 0 | L34: =L29*L32*L33 -> 296017.92 | M34: =M29*M32*M33 -> 294537.83 | N34: =N29*N32*N33 -> 293065.14 | O34: =O29*O32*O33 -> 291599.82 | P34: =P29*P32*P33 -> 290141.82 | Q34: =Q29*Q32*Q33 -> 288691.11 | R34: =R29*R32*R33 -> 287247.65 | ... AU34: =AU29*AU32*AU33 -> 0
C36: Price
D37: PPA
D38: Contracted volume | E38: =Input!E34 -> 0.65 | I38: MWh | K38: =K$34*$E38*K22 -> 0 | L38: =L$34*$E38*L22 -> 192411.65 | M38: =M$34*$E38*M22 -> 191449.59 | N38: =N$34*$E38*N22 -> 190492.34 | O38: =O$34*$E38*O22 -> 189539.88 | P38: =P$34*$E38*P22 -> 188592.18 | Q38: =Q$34*$E38*Q22 -> 187649.22 | R38: =R$34*$E38*R22 -> 186710.97 | ... AU38: =AU$34*$E38*AU22 -> 0
D39: =Input!D35 -> PPA price | E39: =Input!E35 -> 75 | I39: AUD/MWh | K39: =$E39*K22 -> 0 | L39: =$E39*L22 -> 75 | M39: =$E39*M22 -> 75 | N39: =$E39*N22 -> 75 | O39: =$E39*O22 -> 75 | P39: =$E39*P22 -> 75 | Q39: =$E39*Q22 -> 75 | R39: =$E39*R22 -> 75 | ... AU39: =$E39*AU22 -> 0
D40: Total PPA revenue | I40: AUD | K40: =K38*K39 -> 0 | L40: =L38*L39 -> 14430874 | M40: =M38*M39 -> 14358719 | N40: =N38*N39 -> 14286926 | O40: =O38*O39 -> 14215491 | P40: =P38*P39 -> 14144414 | Q40: =Q38*Q39 -> 14073691 | R40: =R38*R39 -> 14003323 | ... AU40: =AU38*AU39 -> 0
D42: Merchant
D43: Merchant volume | I43: MWh | K43: =K34-K38 -> 0 | L43: =L34-L38 -> 103606.27 | M43: =M34-M38 -> 103088.24 | N43: =N34-N38 -> 102572.8 | O43: =O34-O38 -> 102059.94 | P43: =P34-P38 -> 101549.64 | Q43: =Q34-Q38 -> 101041.89 | R43: =R34-R38 -> 100536.68 | ... AU43: =AU34-AU38 -> 0
D44: =Input!D40 -> Spot price (2028) | E44: =Input!E40 -> 55 | I44: AUD/MWh | K44: =$E44 -> 55 | L44: =$E44 -> 55 | M44: =$E44 -> 55 | N44: =$E44 -> 55 | O44: =$E44 -> 55 | P44: =$E44 -> 55 | Q44: =$E44 -> 55 | R44: =$E44 -> 55 | ... AU44: =$E44 -> 55
D45: =Input!D41 -> Spot price escalation | E45: =Input!E41 -> 0.02 | K45: =$E45 -> 0.02 | L45: =$E45 -> 0.02 | M45: =$E45 -> 0.02 | N45: =$E45 -> 0.02 | O45: =$E45 -> 0.02 | P45: =$E45 -> 0.02 | Q45: =$E45 -> 0.02 | R45: =$E45 -> 0.02 | ... AU45: =$E45 -> 0.02
D46: Escalation factor | K46: =IF(K$20=1, 1, J46*(1+K45)) -> 0 | L46: =IF(L$20=1, 1, K46*(1+L45)) -> 1 | M46: =IF(M$20=1, 1, L46*(1+M45)) -> 1.02 | N46: =IF(N$20=1, 1, M46*(1+N45)) -> 1.0404 | O46: =IF(O$20=1, 1, N46*(1+O45)) -> 1.061208 | P46: =IF(P$20=1, 1, O46*(1+P45)) -> 1.0824322 | Q46: =IF(Q$20=1, 1, P46*(1+Q45)) -> 1.1040808 | R46: =IF(R$20=1, 1, Q46*(1+R45)) -> 1.1261624 | ... AU46: =IF(AU$20=1, 1, AT46*(1+AU45)) -> 1.9998896
D47: =Input!D42 -> Negative pricing co-efficient | E47: =Input!E42 -> 0.05 | K47: =$E47 -> 0.05 | L47: =$E47 -> 0.05 | M47: =$E47 -> 0.05 | N47: =$E47 -> 0.05 | O47: =$E47 -> 0.05 | P47: =$E47 -> 0.05 | Q47: =$E47 -> 0.05 | R47: =$E47 -> 0.05 | ... AU47: =$E47 -> 0.05
D48: Total Merchant revenue | I48: AUD | K48: =K43*K44*K46*(1-K47) -> 0 | L48: =L43*L44*L46*(1-L47) -> 5413427.7 | M48: =M43*M44*M46*(1-M47) -> 5494087.8 | N48: =N43*N44*N46*(1-N47) -> 5575949.7 | O48: =O43*O44*O46*(1-O47) -> 5659031.3 | P48: =P43*P44*P46*(1-P47) -> 5743350.9 | Q48: =Q43*Q44*Q46*(1-Q47) -> 5828926.8 | R48: =R43*R44*R46*(1-R47) -> 5915777.8 | ... AU48: =AU43*AU44*AU46*(1-AU47) -> 0
D50: Total Revenue | I50: AUD | K50: =SUM(K40,K48) -> 0 | L50: =SUM(L40,L48) -> 19844301 | M50: =SUM(M40,M48) -> 19852807 | N50: =SUM(N40,N48) -> 19862875 | O50: =SUM(O40,O48) -> 19874522 | P50: =SUM(P40,P48) -> 19887764 | Q50: =SUM(Q40,Q48) -> 19902618 | R50: =SUM(R40,R48) -> 19919101 | ... AU50: =SUM(AU40,AU48) -> 0
B52: Costs
D53: =Input!D46 -> Fixed OPEX & AEMO fees | E53: =Input!E46 -> 4800000 | I53: AUD | K53: =$E53 * K21 -> 0 | L53: =$E53 * L21 -> 4800000 | M53: =$E53 * M21 -> 4800000 | N53: =$E53 * N21 -> 4800000 | O53: =$E53 * O21 -> 4800000 | P53: =$E53 * P21 -> 4800000 | Q53: =$E53 * Q21 -> 4800000 | R53: =$E53 * R21 -> 4800000 | ... AU53: =$E53 * AU21 -> 0
D54: =Input!D47 -> Operating expense escalation | E54: =Input!E47 -> 0.025 | K54: =$E54 -> 0.025 | L54: =$E54 -> 0.025 | M54: =$E54 -> 0.025 | N54: =$E54 -> 0.025 | O54: =$E54 -> 0.025 | P54: =$E54 -> 0.025 | Q54: =$E54 -> 0.025 | R54: =$E54 -> 0.025 | ... AU54: =$E54 -> 0.025
D55: Escalation factor | K55: =IF(K$20=1, 1, J55*(1+K54)) -> 0 | L55: =IF(L$20=1, 1, K55*(1+L54)) -> 1 | M55: =IF(M$20=1, 1, L55*(1+M54)) -> 1.025 | N55: =IF(N$20=1, 1, M55*(1+N54)) -> 1.050625 | O55: =IF(O$20=1, 1, N55*(1+O54)) -> 1.0768906 | P55: =IF(P$20=1, 1, O55*(1+P54)) -> 1.1038129 | Q55: =IF(Q$20=1, 1, P55*(1+Q54)) -> 1.1314082 | R55: =IF(R$20=1, 1, Q55*(1+R54)) -> 1.1596934 | ... AU55: =IF(AU$20=1, 1, AT55*(1+AU54)) -> 2.3732052
D56: Operating expense | I56: AUD | K56: =K53*K55 -> 0 | L56: =L53*L55 -> 4800000 | M56: =M53*M55 -> 4920000 | N56: =N53*N55 -> 5043000 | O56: =O53*O55 -> 5169075 | P56: =P53*P55 -> 5298301.9 | Q56: =Q53*Q55 -> 5430759.4 | R56: =R53*R55 -> 5566528.4 | ... AU56: =AU53*AU55 -> 0
A58: Capital Expenditure
D59: =D14 -> Operating period flag | K59: =K14 -> 0 | L59: =L14 -> 1 | M59: =M14 -> 1 | N59: =N14 -> 1 | O59: =O14 -> 1 | P59: =P14 -> 1 | Q59: =Q14 -> 1 | R59: =R14 -> 1 | ... AU59: =AU14 -> 0
D60: =D$13 -> Construction period flag | K60: =K$13 -> 1 | L60: =L$13 -> 0 | M60: =M$13 -> 0 | N60: =N$13 -> 0 | O60: =O$13 -> 0 | P60: =P$13 -> 0 | Q60: =Q$13 -> 0 | R60: =R$13 -> 0 | ... AU60: =AU$13 -> 0
D61: =D$9 -> COD flag | K61: =K$9 -> 0 | L61: =L$9 -> 1 | M61: =M$9 -> 0 | N61: =N$9 -> 0 | O61: =O$9 -> 0 | P61: =P$9 -> 0 | Q61: =Q$9 -> 0 | R61: =R$9 -> 0 | ... AU61: =AU$9 -> 0
C63: Balance
D64: BoP | I64: AUD | K64: 0 | L64: =K67 -> 2.2856863e+08 | M64: =L67 -> 2.2856863e+08 | N64: =M67 -> 2.2856863e+08 | O64: =N67 -> 2.2856863e+08 | P64: =O67 -> 2.2856863e+08 | Q64: =P67 -> 2.2856863e+08 | R64: =Q67 -> 2.2856863e+08 | S64: =R67 -> 2.2856863e+08 | ... AU64: =AT67 -> 2.2856863e+08
D65: Add: Total EPC & connection cost | E65: =Input!E18 -> 220000000 | I65: AUD | K65: =$E65*K60 -> 220000000 | L65: =$E65*L60 -> 0 | M65: =$E65*M60 -> 0 | N65: =$E65*N60 -> 0 | O65: =$E65*O60 -> 0 | P65: =$E65*P60 -> 0 | Q65: =$E65*Q60 -> 0 | R65: =$E65*R60 -> 0 | ... AU65: =$E65*AU60 -> 0
D66: Add: IDC | I66: AUD | K66: =K161 -> 8568629.8 | L66: =L161 -> 0 | M66: =M161 -> 0 | N66: =N161 -> 0 | O66: =O161 -> 0 | P66: =P161 -> 0 | Q66: =Q161 -> 0 | R66: =R161 -> 0 | ... AU66: =AU161 -> 0
D67: EoP | E67: 0 | I67: AUD | K67: =SUM(K64:K66) -> 2.2856863e+08 | L67: =SUM(L64:L66) -> 2.2856863e+08 | M67: =SUM(M64:M66) -> 2.2856863e+08 | N67: =SUM(N64:N66) -> 2.2856863e+08 | O67: =SUM(O64:O66) -> 2.2856863e+08 | P67: =SUM(P64:P66) -> 2.2856863e+08 | Q67: =SUM(Q64:Q66) -> 2.2856863e+08 | R67: =SUM(R64:R66) -> 2.2856863e+08 | ... AU67: =SUM(AU64:AU66) -> 2.2856863e+08
D69: Total capital expenditure | I69: AUD | K69: =SUM(K65:K65) -> 220000000 | L69: =SUM(L65:L65) -> 0 | M69: =SUM(M65:M65) -> 0 | N69: =SUM(N65:N65) -> 0 | O69: =SUM(O65:O65) -> 0 | P69: =SUM(P65:P65) -> 0 | Q69: =SUM(Q65:Q65) -> 0 | R69: =SUM(R65:R65) -> 0 | ... AU69: =SUM(AU65:AU65) -> 0
D70: Interest during construction | I70: AUD | K70: =K66 -> 8568629.8 | L70: =L66 -> 0 | M70: =M66 -> 0 | N70: =N66 -> 0 | O70: =O66 -> 0 | P70: =P66 -> 0 | Q70: =Q66 -> 0 | R70: =R66 -> 0 | ... AU70: =AU66 -> 0
C72: Depreciation
D73: =Input!D21 -> Useful life | E73: =Input!E21 -> 20 | I73: years
D74: Depreciation flag | G74: =G9 -> 46753 | H74: =EOMONTH(G74-2, E73*12) -> 54057 | J74: =SUM(K74:AU74) -> 20 | K74: =AND(K$4>=$G74, K$5<=$H74) * 1 -> 0 | L74: =AND(L$4>=$G74, L$5<=$H74) * 1 -> 1 | M74: =AND(M$4>=$G74, M$5<=$H74) * 1 -> 1 | N74: =AND(N$4>=$G74, N$5<=$H74) * 1 -> 1 | O74: =AND(O$4>=$G74, O$5<=$H74) * 1 -> 1 | P74: =AND(P$4>=$G74, P$5<=$H74) * 1 -> 1 | Q74: =AND(Q$4>=$G74, Q$5<=$H74) * 1 -> 1 | R74: =AND(R$4>=$G74, R$5<=$H74) * 1 -> 1 | ... AU74: =AND(AU$4>=$G74, AU$5<=$H74) * 1 -> 0
D75: Depreciation expense | I75: AUD | K75: =K64*K74/$J74 -> 0 | L75: =L64*L74/$J74 -> 11428431 | M75: =M64*M74/$J74 -> 11428431 | N75: =N64*N74/$J74 -> 11428431 | O75: =O64*O74/$J74 -> 11428431 | P75: =P64*P74/$J74 -> 11428431 | Q75: =Q64*Q74/$J74 -> 11428431 | R75: =R64*R74/$J74 -> 11428431 | ... AU75: =AU64*AU74/$J74 -> 0
D76: Accumulated depreciation | I76: AUD | K76: =J76+K75 -> 0 | L76: =K76+L75 -> 11428431 | M76: =L76+M75 -> 22856863 | N76: =M76+N75 -> 34285294 | O76: =N76+O75 -> 45713726 | P76: =O76+P75 -> 57142157 | Q76: =P76+Q75 -> 68570589 | R76: =Q76+R75 -> 79999020 | ... AU76: =AT76+AU75 -> 2.2856863e+08
D78: Net plant | I78: AUD | K78: =K67-K76 -> 2.2856863e+08 | L78: =L67-L76 -> 2.171402e+08 | M78: =M67-M76 -> 2.0571177e+08 | N78: =N67-N76 -> 1.9428334e+08 | O78: =O67-O76 -> 1.828549e+08 | P78: =P67-P76 -> 1.7142647e+08 | Q78: =Q67-Q76 -> 1.5999804e+08 | R78: =R67-R76 -> 1.4856961e+08 | ... AU78: =AU67-AU76 -> 0
A80: Income Statement
D81: =D50 -> Total Revenue | I81: AUD | J81: =SUM(K81:AU81) -> 7.3743906e+08 | K81: =K50 -> 0 | L81: =L50 -> 19844301 | M81: =M50 -> 19852807 | N81: =N50 -> 19862875 | O81: =O50 -> 19874522 | P81: =P50 -> 19887764 | Q81: =Q50 -> 19902618 | R81: =R50 -> 19919101 | ... AU81: =AU50 -> 0
D82: =D56 -> Operating expense | I82: AUD | J82: =SUM(K82:AU82) -> -2.636554e+08 | K82: =-K56 -> 0 | L82: =-L56 -> -4800000 | M82: =-M56 -> -4920000 | N82: =-N56 -> -5043000 | O82: =-O56 -> -5169075 | P82: =-P56 -> -5298301.9 | Q82: =-Q56 -> -5430759.4 | R82: =-R56 -> -5566528.4 | ... AU82: =-AU56 -> 0
D83: EBITDA | I83: AUD | J83: =SUM(K83:AU83) -> 4.7378367e+08 | K83: =SUM(K81:K82) -> 0 | L83: =SUM(L81:L82) -> 15044301 | M83: =SUM(M81:M82) -> 14932807 | N83: =SUM(N81:N82) -> 14819875 | O83: =SUM(O81:O82) -> 14705447 | P83: =SUM(P81:P82) -> 14589463 | Q83: =SUM(Q81:Q82) -> 14471859 | R83: =SUM(R81:R82) -> 14352572 | ... AU83: =SUM(AU81:AU82) -> 0
D84: % of revenue | J84: =AVERAGE(K84:AU84) -> 0.61153327 | K84: =IFERROR(K83/K$81,0) -> 0 | L84: =IFERROR(L83/L$81,0) -> 0.75811696 | M84: =IFERROR(M83/M$81,0) -> 0.7521761 | N84: =IFERROR(N83/N$81,0) -> 0.74610927 | O84: =IFERROR(O83/O$81,0) -> 0.7399145 | P84: =IFERROR(P83/P$81,0) -> 0.73358987 | Q84: =IFERROR(Q83/Q$81,0) -> 0.72713342 | R84: =IFERROR(R83/R$81,0) -> 0.72054319 | ... AU84: =IFERROR(AU83/AU$81,0) -> 0
D85: =D75 -> Depreciation expense | I85: AUD | J85: =SUM(K85:AU85) -> -2.2856863e+08 | K85: =-K75 -> 0 | L85: =-L75 -> -11428431 | M85: =-M75 -> -11428431 | N85: =-N75 -> -11428431 | O85: =-O75 -> -11428431 | P85: =-P75 -> -11428431 | Q85: =-Q75 -> -11428431 | R85: =-R75 -> -11428431 | ... AU85: =-AU75 -> 0
D86: EBIT | I86: AUD | J86: =SUM(K86:AU86) -> 2.4521504e+08 | K86: =SUM(K83,K85) -> 0 | L86: =SUM(L83,L85) -> 3615869.8 | M86: =SUM(M83,M85) -> 3504375.5 | N86: =SUM(N83,N85) -> 3391443.8 | O86: =SUM(O83,O85) -> 3277015.9 | P86: =SUM(P83,P85) -> 3161031.1 | Q86: =SUM(Q83,Q85) -> 3043427.4 | R86: =SUM(R83,R85) -> 2924141 | ... AU86: =SUM(AU83,AU85) -> 0
D87: % of revenue | J87: =AVERAGE(K87:AU87) -> 0.29503093 | K87: =IFERROR(K86/K$81,0) -> 0 | L87: =IFERROR(L86/L$81,0) -> 0.182212 | M87: =IFERROR(M86/M$81,0) -> 0.17651789 | N87: =IFERROR(N86/N$81,0) -> 0.17074284 | O87: =IFERROR(O86/O$81,0) -> 0.16488526 | P87: =IFERROR(P86/P$81,0) -> 0.15894351 | Q87: =IFERROR(Q86/Q$81,0) -> 0.15291593 | R87: =IFERROR(R86/R$81,0) -> 0.14680085 | ... AU87: =IFERROR(AU86/AU$81,0) -> 0
D88: Interest expense | I88: AUD | J88: =SUM(K88:AU88) -> -38426692 | K88: =-K162 -> 0 | L88: =-L162 -> -8568629.8 | M88: =-M162 -> -8147711.2 | N88: =-N162 -> -7706680 | O88: =-O162 -> -7244322.3 | P88: =-P162 -> -6759349.1 | Q88: =-Q162 -> 0 | R88: =-R162 -> 0 | ... AU88: =-AU162 -> 0
D89: Profit before tax | I89: AUD | J89: =SUM(K89:AU89) -> 2.0678834e+08 | K89: =SUM(K86,K88:K88) -> 0 | L89: =SUM(L86,L88:L88) -> -4952760 | M89: =SUM(M86,M88:M88) -> -4643335.7 | N89: =SUM(N86,N88:N88) -> -4315236.1 | O89: =SUM(O86,O88:O88) -> -3967306.4 | P89: =SUM(P86,P88:P88) -> -3598318 | Q89: =SUM(Q86,Q88:Q88) -> 3043427.4 | R89: =SUM(R86,R88:R88) -> 2924141 | ... AU89: =SUM(AU86,AU88:AU88) -> 0
C91: NOL
D92: BoP | I92: AUD | K92: 0 | L92: =K95 -> 0 | M92: =L95 -> 4952760 | N92: =M95 -> 9596095.7 | O92: =N95 -> 13911332 | P92: =O95 -> 17878638 | Q92: =P95 -> 21476956 | R92: =Q95 -> 18433529 | S92: =R95 -> 15509388 | ... AU92: =AT95 -> 0
D93: Add: new loss | I93: AUD | J93: =SUM(K93:AU93) -> 21476956 | K93: =-MIN(K89,0) -> 0 | L93: =-MIN(L89,0) -> 4952760 | M93: =-MIN(M89,0) -> 4643335.7 | N93: =-MIN(N89,0) -> 4315236.1 | O93: =-MIN(O89,0) -> 3967306.4 | P93: =-MIN(P89,0) -> 3598318 | Q93: =-MIN(Q89,0) -> 0 | R93: =-MIN(R89,0) -> 0 | ... AU93: =-MIN(AU89,0) -> 0
D94: Less: loss utilised | I94: AUD | J94: =SUM(K94:AU94) -> -21476956 | K94: =-MIN(K92,MAX(K89,0)) -> 0 | L94: =-MIN(L92,MAX(L89,0)) -> 0 | M94: =-MIN(M92,MAX(M89,0)) -> 0 | N94: =-MIN(N92,MAX(N89,0)) -> 0 | O94: =-MIN(O92,MAX(O89,0)) -> 0 | P94: =-MIN(P92,MAX(P89,0)) -> 0 | Q94: =-MIN(Q92,MAX(Q89,0)) -> -3043427.4 | R94: =-MIN(R92,MAX(R89,0)) -> -2924141 | ... AU94: =-MIN(AU92,MAX(AU89,0)) -> 0
D95: EoP | I95: AUD | K95: =SUM(K92:K94) -> 0 | L95: =SUM(L92:L94) -> 4952760 | M95: =SUM(M92:M94) -> 9596095.7 | N95: =SUM(N92:N94) -> 13911332 | O95: =SUM(O92:O94) -> 17878638 | P95: =SUM(P92:P94) -> 21476956 | Q95: =SUM(Q92:Q94) -> 18433529 | R95: =SUM(R92:R94) -> 15509388 | ... AU95: =SUM(AU92:AU94) -> 0
D96: Adjusted taxable income | I96: AUD | J96: =SUM(K96:AU96) -> 2.0678834e+08 | K96: =MAX(K89+K94, 0) -> 0 | L96: =MAX(L89+L94, 0) -> 0 | M96: =MAX(M89+M94, 0) -> 0 | N96: =MAX(N89+N94, 0) -> 0 | O96: =MAX(O89+O94, 0) -> 0 | P96: =MAX(P89+P94, 0) -> 0 | Q96: =MAX(Q89+Q94, 0) -> 0 | R96: =MAX(R89+R94, 0) -> 0 | ... AU96: =MAX(AU89+AU94, 0) -> 0
D98: Tax expense | E98: =Input!E54 -> 0.3 | I98: AUD | J98: =SUM(K98:AU98) -> 62036503 | K98: =MAX(K96,0)*$E98 -> 0 | L98: =MAX(L96,0)*$E98 -> 0 | M98: =MAX(M96,0)*$E98 -> 0 | N98: =MAX(N96,0)*$E98 -> 0 | O98: =MAX(O96,0)*$E98 -> 0 | P98: =MAX(P96,0)*$E98 -> 0 | Q98: =MAX(Q96,0)*$E98 -> 0 | R98: =MAX(R96,0)*$E98 -> 0 | ... AU98: =MAX(AU96,0)*$E98 -> 0
D99: Net profit | I99: AUD | J99: =SUM(K99:AU99) -> 1.4475184e+08 | K99: =K89-K98 -> 0 | L99: =L89-L98 -> -4952760 | M99: =M89-M98 -> -4643335.7 | N99: =N89-N98 -> -4315236.1 | O99: =O89-O98 -> -3967306.4 | P99: =P89-P98 -> -3598318 | Q99: =Q89-Q98 -> 3043427.4 | R99: =R89-R98 -> 2924141 | ... AU99: =AU89-AU98 -> 0
D100: % of revenue | J100: =AVERAGE(K100:AU100) -> 0.16998953 | K100: =IFERROR(K99/K$81,0) -> 0 | L100: =IFERROR(L99/L$81,0) -> -0.24958097 | M100: =IFERROR(M99/M$81,0) -> -0.23388812 | N100: =IFERROR(N99/N$81,0) -> -0.21725133 | O100: =IFERROR(O99/O$81,0) -> -0.1996177 | P100: =IFERROR(P99/P$81,0) -> -0.18093125 | Q100: =IFERROR(Q99/Q$81,0) -> 0.15291593 | R100: =IFERROR(R99/R$81,0) -> 0.14680085 | ... AU100: =IFERROR(AU99/AU$81,0) -> 0
D102: Unlevered tax expense | I102: AUD | J102: =SUM(K102:AU102) -> 73564511 | K102: =K86*$E98 -> 0 | L102: =L86*$E98 -> 1084760.9 | M102: =M86*$E98 -> 1051312.7 | N102: =N86*$E98 -> 1017433.2 | O102: =O86*$E98 -> 983104.76 | P102: =P86*$E98 -> 948309.33 | Q102: =Q86*$E98 -> 913028.22 | R102: =R86*$E98 -> 877242.29 | ... AU102: =AU86*$E98 -> 0
B104: Working Capital
C105: Accounts Receivables
D106: =D81 -> Total Revenue | I106: AUD | K106: =K81 -> 0 | L106: =L81 -> 19844301 | M106: =M81 -> 19852807 | N106: =N81 -> 19862875 | O106: =O81 -> 19874522 | P106: =P81 -> 19887764 | Q106: =Q81 -> 19902618 | R106: =R81 -> 19919101 | ... AU106: =AU81 -> 0
D107: Days in period | K107: =K$5-J$5+1 -> 366 | L107: =L$5-L$4+1 -> 366 | M107: =M$5-M$4+1 -> 365 | N107: =N$5-N$4+1 -> 365 | O107: =O$5-O$4+1 -> 365 | P107: =P$5-P$4+1 -> 366 | Q107: =Q$5-Q$4+1 -> 365 | R107: =R$5-R$4+1 -> 365 | S107: =S$5-S$4+1 -> 365 | ... AU107: =AU$5-AU$4+1 -> 365
D108: AR days | E108: =Input!E50 -> 0 | K108: =$E108 -> 0 | L108: =$E108 -> 0 | M108: =$E108 -> 0 | N108: =$E108 -> 0 | O108: =$E108 -> 0 | P108: =$E108 -> 0 | Q108: =$E108 -> 0 | R108: =$E108 -> 0 | ... AU108: =$E108 -> 0
D109: Account receivables | I109: AUD | K109: =K106*K108/K107 -> 0 | L109: =L106*L108/L107 -> 0 | M109: =M106*M108/M107 -> 0 | N109: =N106*N108/N107 -> 0 | O109: =O106*O108/O107 -> 0 | P109: =P106*P108/P107 -> 0 | Q109: =Q106*Q108/Q107 -> 0 | R109: =R106*R108/R107 -> 0 | ... AU109: =AU106*AU108/AU107 -> 0
C111: Accounts Payables
D112: =D82 -> Operating expense | I112: AUD | K112: =-K82 -> 0 | L112: =-L82 -> 4800000 | M112: =-M82 -> 4920000 | N112: =-N82 -> 5043000 | O112: =-O82 -> 5169075 | P112: =-P82 -> 5298301.9 | Q112: =-Q82 -> 5430759.4 | R112: =-R82 -> 5566528.4 | ... AU112: =-AU82 -> 0
D113: Days in period | K113: =K$5-J$5+1 -> 366 | L113: =L$5-L$4+1 -> 366 | M113: =M$5-M$4+1 -> 365 | N113: =N$5-N$4+1 -> 365 | O113: =O$5-O$4+1 -> 365 | P113: =P$5-P$4+1 -> 366 | Q113: =Q$5-Q$4+1 -> 365 | R113: =R$5-R$4+1 -> 365 | S113: =S$5-S$4+1 -> 365 | ... AU113: =AU$5-AU$4+1 -> 365
D114: AP days | E114: =Input!E51 -> 0 | K114: =$E114 -> 0 | L114: =$E114 -> 0 | M114: =$E114 -> 0 | N114: =$E114 -> 0 | O114: =$E114 -> 0 | P114: =$E114 -> 0 | Q114: =$E114 -> 0 | R114: =$E114 -> 0 | ... AU114: =$E114 -> 0
D115: Account payables | I115: AUD | K115: =K112*K114/K113 -> 0 | L115: =L112*L114/L113 -> 0 | M115: =M112*M114/M113 -> 0 | N115: =N112*N114/N113 -> 0 | O115: =O112*O114/O113 -> 0 | P115: =P112*P114/P113 -> 0 | Q115: =Q112*Q114/Q113 -> 0 | R115: =R112*R114/R113 -> 0 | ... AU115: =AU112*AU114/AU113 -> 0
D117: Working capital | I117: AUD | K117: =K109-K115 -> 0 | L117: =L109-L115 -> 0 | M117: =M109-M115 -> 0 | N117: =N109-N115 -> 0 | O117: =O109-O115 -> 0 | P117: =P109-P115 -> 0 | Q117: =Q109-Q115 -> 0 | R117: =R109-R115 -> 0 | ... AU117: =AU109-AU115 -> 0
D118: Changes in working capital | I118: AUD | J118: =SUM(K118:AU118) -> 0 | K118: =K117-J117 -> 0 | L118: =L117-K117 -> 0 | M118: =M117-L117 -> 0 | N118: =N117-M117 -> 0 | O118: =O117-N117 -> 0 | P118: =P117-O117 -> 0 | Q118: =Q117-P117 -> 0 | R118: =R117-Q117 -> 0 | ... AU118: =AU117-AT117 -> 0
B120: CFADS
D121: =D83 -> EBITDA | I121: AUD | J121: =SUM(K121:AU121) -> 4.7378367e+08 | K121: =K83 -> 0 | L121: =L83 -> 15044301 | M121: =M83 -> 14932807 | N121: =N83 -> 14819875 | O121: =O83 -> 14705447 | P121: =P83 -> 14589463 | Q121: =Q83 -> 14471859 | R121: =R83 -> 14352572 | ... AU121: =AU83 -> 0
D122: ="Less: "&D69 -> Less: Total capital expenditure | I122: AUD | J122: =SUM(K122:AU122) -> -220000000 | K122: =-K69 -> -220000000 | L122: =-L69 -> 0 | M122: =-M69 -> 0 | N122: =-N69 -> 0 | O122: =-O69 -> 0 | P122: =-P69 -> 0 | Q122: =-Q69 -> 0 | R122: =-R69 -> 0 | ... AU122: =-AU69 -> 0
...

Sheet FS
A1: Financial Statements
D2: Year | F2: =Model!K6 -> 2027 | G2: =Model!L6 -> 2028 | H2: =Model!M6 -> 2029 | I2: =Model!N6 -> 2030 | J2: =Model!O6 -> 2031 | K2: =Model!P6 -> 2032 | L2: =Model!Q6 -> 2033 | M2: =Model!R6 -> 2034 | ... AP2: =Model!AU6 -> 2063
E3: Unit
A4: Income Statement
D5: =Model!D81 -> Total Revenue | E5: AUD | F5: =Model!K81 -> 0 | G5: =Model!L81 -> 19844301 | H5: =Model!M81 -> 19852807 | I5: =Model!N81 -> 19862875 | J5: =Model!O81 -> 19874522 | K5: =Model!P81 -> 19887764 | L5: =Model!Q81 -> 19902618 | M5: =Model!R81 -> 19919101 | ... AP5: =Model!AU81 -> 0
D6: =Model!D82 -> Operating expense | E6: AUD | F6: =Model!K82 -> 0 | G6: =Model!L82 -> -4800000 | H6: =Model!M82 -> -4920000 | I6: =Model!N82 -> -5043000 | J6: =Model!O82 -> -5169075 | K6: =Model!P82 -> -5298301.9 | L6: =Model!Q82 -> -5430759.4 | M6: =Model!R82 -> -5566528.4 | ... AP6: =Model!AU82 -> 0
D7: =Model!D83 -> EBITDA | E7: AUD | F7: =Model!K83 -> 0 | G7: =Model!L83 -> 15044301 | H7: =Model!M83 -> 14932807 | I7: =Model!N83 -> 14819875 | J7: =Model!O83 -> 14705447 | K7: =Model!P83 -> 14589463 | L7: =Model!Q83 -> 14471859 | M7: =Model!R83 -> 14352572 | ... AP7: =Model!AU83 -> 0
D8: =Model!D84 -> % of revenue | F8: =Model!K84 -> 0 | G8: =Model!L84 -> 0.75811696 | H8: =Model!M84 -> 0.7521761 | I8: =Model!N84 -> 0.74610927 | J8: =Model!O84 -> 0.7399145 | K8: =Model!P84 -> 0.73358987 | L8: =Model!Q84 -> 0.72713342 | M8: =Model!R84 -> 0.72054319 | ... AP8: =Model!AU84 -> 0
D9: =Model!D85 -> Depreciation expense | E9: AUD | F9: =Model!K85 -> 0 | G9: =Model!L85 -> -11428431 | H9: =Model!M85 -> -11428431 | I9: =Model!N85 -> -11428431 | J9: =Model!O85 -> -11428431 | K9: =Model!P85 -> -11428431 | L9: =Model!Q85 -> -11428431 | M9: =Model!R85 -> -11428431 | ... AP9: =Model!AU85 -> 0
D10: =Model!D86 -> EBIT | E10: AUD | F10: =Model!K86 -> 0 | G10: =Model!L86 -> 3615869.8 | H10: =Model!M86 -> 3504375.5 | I10: =Model!N86 -> 3391443.8 | J10: =Model!O86 -> 3277015.9 | K10: =Model!P86 -> 3161031.1 | L10: =Model!Q86 -> 3043427.4 | M10: =Model!R86 -> 2924141 | ... AP10: =Model!AU86 -> 0
D11: =Model!D87 -> % of revenue | F11: =Model!K87 -> 0 | G11: =Model!L87 -> 0.182212 | H11: =Model!M87 -> 0.17651789 | I11: =Model!N87 -> 0.17074284 | J11: =Model!O87 -> 0.16488526 | K11: =Model!P87 -> 0.15894351 | L11: =Model!Q87 -> 0.15291593 | M11: =Model!R87 -> 0.14680085 | ... AP11: =Model!AU87 -> 0
D12: =Model!D88 -> Interest expense | E12: AUD | F12: =Model!K88 -> 0 | G12: =Model!L88 -> -8568629.8 | H12: =Model!M88 -> -8147711.2 | I12: =Model!N88 -> -7706680 | J12: =Model!O88 -> -7244322.3 | K12: =Model!P88 -> -6759349.1 | L12: =Model!Q88 -> 0 | M12: =Model!R88 -> 0 | ... AP12: =Model!AU88 -> 0
D13: =Model!D89 -> Profit before tax | E13: AUD | F13: =Model!K89 -> 0 | G13: =Model!L89 -> -4952760 | H13: =Model!M89 -> -4643335.7 | I13: =Model!N89 -> -4315236.1 | J13: =Model!O89 -> -3967306.4 | K13: =Model!P89 -> -3598318 | L13: =Model!Q89 -> 3043427.4 | M13: =Model!R89 -> 2924141 | ... AP13: =Model!AU89 -> 0
D14: =Model!D98 -> Tax expense | E14: AUD | F14: =Model!K98 -> 0 | G14: =Model!L98 -> 0 | H14: =Model!M98 -> 0 | I14: =Model!N98 -> 0 | J14: =Model!O98 -> 0 | K14: =Model!P98 -> 0 | L14: =Model!Q98 -> 0 | M14: =Model!R98 -> 0 | ... AP14: =Model!AU98 -> 0
D15: =Model!D99 -> Net profit | E15: AUD | F15: =Model!K99 -> 0 | G15: =Model!L99 -> -4952760 | H15: =Model!M99 -> -4643335.7 | I15: =Model!N99 -> -4315236.1 | J15: =Model!O99 -> -3967306.4 | K15: =Model!P99 -> -3598318 | L15: =Model!Q99 -> 3043427.4 | M15: =Model!R99 -> 2924141 | ... AP15: =Model!AU99 -> 0
A17: Cash Flow Statement
D18: =Model!D206 -> EBITDA | E18: AUD | F18: =Model!K206 -> 0 | G18: =Model!L206 -> 15044301 | H18: =Model!M206 -> 14932807 | I18: =Model!N206 -> 14819875 | J18: =Model!O206 -> 14705447 | K18: =Model!P206 -> 14589463 | L18: =Model!Q206 -> 14471859 | M18: =Model!R206 -> 14352572 | ... AP18: =Model!AU206 -> 0
D19: =Model!D207 -> Total capital expenditure | E19: AUD | F19: =Model!K207 -> -220000000 | G19: =Model!L207 -> 0 | H19: =Model!M207 -> 0 | I19: =Model!N207 -> 0 | J19: =Model!O207 -> 0 | K19: =Model!P207 -> 0 | L19: =Model!Q207 -> 0 | M19: =Model!R207 -> 0 | ... AP19: =Model!AU207 -> 0
D20: =Model!D208 -> Interest during construction | E20: AUD | F20: =Model!K208 -> -8568629.8 | G20: =Model!L208 -> 0 | H20: =Model!M208 -> 0 | I20: =Model!N208 -> 0 | J20: =Model!O208 -> 0 | K20: =Model!P208 -> 0 | L20: =Model!Q208 -> 0 | M20: =Model!R208 -> 0 | ... AP20: =Model!AU208 -> 0
D21: =Model!D209 -> Changes in working capital | E21: AUD | F21: =Model!K209 -> 0 | G21: =Model!L209 -> 0 | H21: =Model!M209 -> 0 | I21: =Model!N209 -> 0 | J21: =Model!O209 -> 0 | K21: =Model!P209 -> 0 | L21: =Model!Q209 -> 0 | M21: =Model!R209 -> 0 | ... AP21: =Model!AU209 -> 0
D22: =Model!D210 -> Tax expense | E22: AUD | F22: =Model!K210 -> 0 | G22: =Model!L210 -> 0 | H22: =Model!M210 -> 0 | I22: =Model!N210 -> 0 | J22: =Model!O210 -> 0 | K22: =Model!P210 -> 0 | L22: =Model!Q210 -> 0 | M22: =Model!R210 -> 0 | ... AP22: =Model!AU210 -> 0
D23: =Model!D211 -> Cash available before debt service | E23: AUD | F23: =Model!K211 -> -2.2856863e+08 | G23: =Model!L211 -> 15044301 | H23: =Model!M211 -> 14932807 | I23: =Model!N211 -> 14819875 | J23: =Model!O211 -> 14705447 | K23: =Model!P211 -> 14589463 | L23: =Model!Q211 -> -81688014 | M23: =Model!R211 -> -67335442 | ... AP23: =Model!AU211 -> 0
D25: =Model!D213 -> Equity contribution | E25: AUD | F25: =Model!K213 -> 96743555 | G25: =Model!L213 -> 0 | H25: =Model!M213 -> 0 | I25: =Model!N213 -> 0 | J25: =Model!O213 -> 0 | K25: =Model!P213 -> 0 | L25: =Model!Q213 -> 0 | M25: =Model!R213 -> 0 | ... AP25: =Model!AU213 -> 0
D26: =Model!D214 -> Debt drawdown | E26: AUD | F26: =Model!K214 -> 1.3182507e+08 | G26: =Model!L214 -> 0 | H26: =Model!M214 -> 0 | I26: =Model!N214 -> 0 | J26: =Model!O214 -> 0 | K26: =Model!P214 -> 0 | L26: =Model!Q214 -> 0 | M26: =Model!R214 -> 0 | ... AP26: =Model!AU214 -> 0
D27: =Model!D215 -> Scheduled repayment | E27: AUD | F27: =Model!K215 -> 0 | G27: =Model!L215 -> -2238585 | H27: =Model!M215 -> -2659503.7 | I27: =Model!N215 -> -3100534.9 | J27: =Model!O215 -> -3562892.6 | K27: =Model!P215 -> -4047865.7 | L27: =Model!Q215 -> 0 | M27: =Model!R215 -> 0 | ... AP27: =Model!AU215 -> 0
D28: =Model!D216 -> Interest paid | E28: AUD | F28: =Model!K216 -> 0 | G28: =Model!L216 -> -8568629.8 | H28: =Model!M216 -> -8147711.2 | I28: =Model!N216 -> -7706680 | J28: =Model!O216 -> -7244322.3 | K28: =Model!P216 -> -6759349.1 | L28: =Model!Q216 -> 0 | M28: =Model!R216 -> 0 | ... AP28: =Model!AU216 -> 0
D29: =Model!D217 -> Cash available for prepayment | E29: AUD | F29: =Model!K217 -> 0 | G29: =Model!L217 -> 4237086.5 | H29: =Model!M217 -> 4125592.2 | I29: =Model!N217 -> 4012660.5 | J29: =Model!O217 -> 3898232.5 | K29: =Model!P217 -> 3782247.7 | L29: =Model!Q217 -> -81688014 | M29: =Model!R217 -> -67335442 | ... AP29: =Model!AU217 -> 0
D31: =Model!D219 -> Cash sweep prepayment | E31: AUD | F31: =Model!K219 -> 0 | G31: =Model!L219 -> -4237086.5 | H31: =Model!M219 -> -4125592.2 | I31: =Model!N219 -> -4012660.5 | J31: =Model!O219 -> -3898232.5 | K31: =Model!P219 -> -3782247.7 | L31: =Model!Q219 -> 0 | M31: =Model!R219 -> 0 | ... AP31: =Model!AU219 -> 0
... D35: =Model!D223 -> Dividends | E35: AUD | F35: =Model!K223 -> 0 | G35: =Model!L223 -> 0 | H35: =Model!M223 -> 0 | I35: =Model!N223 -> 0 | J35: =Model!O223 -> 0 | K35: =Model!P223 -> 0 | L35: =Model!Q223 -> 0 | M35: =Model!R223 -> 0 | ... AP35: =Model!AU223 -> 0
D36: =Model!D227 -> Net cash flow | E36: AUD | F36: =Model!K227 -> 0 | G36: =Model!L227 -> 0 | H36: =Model!M227 -> 0 | I36: =Model!N227 -> 0 | J36: =Model!O227 -> 0 | K36: =Model!P227 -> -96159873 | L36: =Model!Q227 -> 14471859 | M36: =Model!R227 -> 14352572 | ... AP36: =Model!AU227 -> 0
A38: Balance Sheet
C39: Asset | E39: AUD
D40: =Model!D267 -> Cash | E40: AUD | F40: =Model!K267 -> 0 | G40: =Model!L267 -> 0 | H40: =Model!M267 -> 0 | I40: =Model!N267 -> 0 | J40: =Model!O267 -> 0 | K40: =Model!P267 -> -96159873 | L40: =Model!Q267 -> -81688014 | M40: =Model!R267 -> -67335442 | ... AP40: =Model!AU267 -> 0
D41: =Model!D268 -> Account receivables | E41: AUD | F41: =Model!K268 -> 0 | G41: =Model!L268 -> 0 | H41: =Model!M268 -> 0 | I41: =Model!N268 -> 0 | J41: =Model!O268 -> 0 | K41: =Model!P268 -> 0 | L41: =Model!Q268 -> 0 | M41: =Model!R268 -> 0 | ... AP41: =Model!AU268 -> 0
D42: =Model!D269 -> Net plant | E42: AUD | F42: =Model!K269 -> 2.2856863e+08 | G42: =Model!L269 -> 2.171402e+08 | H42: =Model!M269 -> 2.0571177e+08 | I42: =Model!N269 -> 1.9428334e+08 | J42: =Model!O269 -> 1.828549e+08 | K42: =Model!P269 -> 1.7142647e+08 | L42: =Model!Q269 -> 1.5999804e+08 | M42: =Model!R269 -> 1.4856961e+08 | ... AP42: =Model!AU269 -> 0
D43: =Model!D270 -> Total Asset | E43: AUD | F43: =Model!K270 -> 2.2856863e+08 | G43: =Model!L270 -> 2.171402e+08 | H43: =Model!M270 -> 2.0571177e+08 | I43: =Model!N270 -> 1.9428334e+08 | J43: =Model!O270 -> 1.828549e+08 | K43: =Model!P270 -> 75266599 | L43: =Model!Q270 -> 78310027 | M43: =Model!R270 -> 81234168 | ... AP43: =Model!AU270 -> 0
C45: Liability | E45: AUD
D46: =Model!D273 -> Senior debt | E46: AUD | F46: =Model!K273 -> 1.3182507e+08 | G46: =Model!L273 -> 1.253494e+08 | H46: =Model!M273 -> 1.1856431e+08 | I46: =Model!N273 -> 1.1145111e+08 | J46: =Model!O273 -> 1.0398999e+08 | K46: =Model!P273 -> 0 | L46: =Model!Q273 -> 0 | M46: =Model!R273 -> 0 | ... AP46: =Model!AU273 -> 0
D47: =Model!D274 -> Total Liability | E47: AUD | F47: =Model!K274 -> 1.3182507e+08 | G47: =Model!L274 -> 1.253494e+08 | H47: =Model!M274 -> 1.1856431e+08 | I47: =Model!N274 -> 1.1145111e+08 | J47: =Model!O274 -> 1.0398999e+08 | K47: =Model!P274 -> 0 | L47: =Model!Q274 -> 0 | M47: =Model!R274 -> 0 | ... AP47: =Model!AU274 -> 0
C49: Equity | E49: AUD
D50: =Model!D277 -> Share capital | E50: AUD | F50: =Model!K277 -> 96743555 | G50: =Model!L277 -> 96743555 | H50: =Model!M277 -> 96743555 | I50: =Model!N277 -> 96743555 | J50: =Model!O277 -> 96743555 | K50: =Model!P277 -> 96743555 | L50: =Model!Q277 -> 96743555 | M50: =Model!R277 -> 96743555 | ... AP50: =Model!AU277 -> 96743555
D51: =Model!D278 -> Retained earnings | E51: AUD | F51: =Model!K278 -> 0 | G51: =Model!L278 -> -4952760 | H51: =Model!M278 -> -9596095.7 | I51: =Model!N278 -> -13911332 | J51: =Model!O278 -> -17878638 | K51: =Model!P278 -> -21476956 | L51: =Model!Q278 -> -18433529 | M51: =Model!R278 -> -15509388 | ... AP51: =Model!AU278 -> -96743555
D52: =Model!D279 -> Total Equity | E52: AUD | F52: =Model!K279 -> 96743555 | G52: =Model!L279 -> 91790795 | H52: =Model!M279 -> 87147460 | I52: =Model!N279 -> 82832224 | J52: =Model!O279 -> 78864917 | K52: =Model!P279 -> 75266599 | L52: =Model!Q279 -> 78310027 | M52: =Model!R279 -> 81234168 | ... AP52: =Model!AU279 -> 0
D54: =Model!D281 -> Check | E54: =SUM(F54:AP54)=0 -> TRUE | F54: =(F43<>(F47+F52))*1 -> 0 | G54: =(G43<>(G47+G52))*1 -> 0 | H54: =(H43<>(H47+H52))*1 -> 0 | I54: =(I43<>(I47+I52))*1 -> 0 | J54: =(J43<>(J47+J52))*1 -> 0 | K54: =(K43<>(K47+K52))*1 -> 0 | L54: =(L43<>(L47+L52))*1 -> 0 | M54: =(M43<>(M47+M52))*1 -> 0 | ... AP54: =(AP43<>(AP47+AP52))*1 -> 0
